handlerutil/__init__.py
handlerutil/call_with_handlers_decorator.py
handlerutil/handler.py
handlerutil/handler_kind.py
handlerutil/handlers.py
handlerutil/iterate_with_handlers.py
handlerutil-0.0.1.dist-info/METADATA
handlerutil-0.0.1.dist-info/WHEEL
handlerutil-0.0.1.dist-info/licenses/LICENSE
handlerutil-0.0.1.dist-info/RECORD
